smartsearch/__init__.py
smartsearch/server.py
mcp_smartsearch-0.1.5.dist-info/METADATA
mcp_smartsearch-0.1.5.dist-info/WHEEL
mcp_smartsearch-0.1.5.dist-info/entry_points.txt
mcp_smartsearch-0.1.5.dist-info/top_level.txt
mcp_smartsearch-0.1.5.dist-info/RECORD
