Metadata-Version: 2.4
Name: mcp-smartsearch
Version: 0.1.5
Summary: A smart search MCP server.
Requires-Python: >=3.10
Requires-Dist: mcp[cli]>=1.10.1
